pytorch_inferno/__init__.py
pytorch_inferno/_nbdev.py
pytorch_inferno/callback.py
pytorch_inferno/data.py
pytorch_inferno/inference.py
pytorch_inferno/inferno.py
pytorch_inferno/inferno_interp.py
pytorch_inferno/model_wrapper.py
pytorch_inferno/plotting.py
pytorch_inferno/pseudodata.py
pytorch_inferno/utils.py
pytorch_inferno-0.2.2.dist-info/METADATA
pytorch_inferno-0.2.2.dist-info/RECORD
pytorch_inferno-0.2.2.dist-info/WHEEL
pytorch_inferno-0.2.2.dist-info/entry_points.txt
pytorch_inferno-0.2.2.dist-info/top_level.txt
