Metadata-Version: 2.1
Name: pytorch-inferno
Version: 0.2.2
Summary: PyTorch Implementation of INFERNO
Home-page: https://github.com/GilesStrong/pytorch_inferno/tree/master/
Author: Giles Strong
Author-email: giles.strong@outlook.com
License: Apache Software License 2.0
Keywords: INFERNO,HEP,inference
Platform: UNKNOWN
Classifier: Development Status :: 5 - Production/Stable
Classifier: Intended Audience :: Developers
Classifier: License :: OSI Approved :: Apache Software License
Classifier: Natural Language :: English
Classifier: Programming Language :: Python :: 3.6
Classifier: Programming Language :: Python :: 3.7
Classifier: Programming Language :: Python :: 3.8
Requires-Python: >=3.6
Requires-Dist: torch (>=1.7)
Requires-Dist: fastcore
Requires-Dist: numpy
Requires-Dist: pandas
Requires-Dist: fastprogress
Requires-Dist: matplotlib (>=3.0.0)
Requires-Dist: seaborn
Requires-Dist: scipy
